inpromptu/__init__.py
inpromptu/errors.py
inpromptu/inpromptu_base.py
inpromptu/inpromptu_old.py
inpromptu/inpromptu_prompt_toolkit.py
inpromptu/inpromptu_readline.py
inpromptu/object_method_manager.py
tests/__init__.py
tests/basic_tests.py
tests/completion_tests.py
tests/decorator_tests.py
tests/inheritance_tests.py
tests/ownership_tests.py
tests/test_classes.py
inpromptu-0.1.1.dist-info/LICENSE.txt
inpromptu-0.1.1.dist-info/METADATA
inpromptu-0.1.1.dist-info/WHEEL
inpromptu-0.1.1.dist-info/top_level.txt
inpromptu-0.1.1.dist-info/RECORD
