Metadata-Version: 2.1
Name: inpromptu
Version: 0.1.1
Summary: An inferrable line oriented command prompt interpreter
Home-page: https://github.com/poofjunior/inpromptu
Author: Joshua Vasquez
Author-email: joshua@doublejumpelectric.com
License: MIT
Keywords: interpreter,inspection,prompt,repl
Classifier: Development Status :: 4 - Beta
Classifier: Programming Language :: Python :: 3
Classifier: License :: OSI Approved :: MIT License
Classifier: Operating System :: POSIX :: Linux
Requires-Python: >=3.6
License-File: LICENSE.txt
Requires-Dist: prompt-toolkit (>=3.0.28)
